README.rst
setup.cfg
setup.py
peek_server/PeekServerConfig.py
peek_server/__init__.py
peek_server/alembic.ini
peek_server/run_peek_server.py
peek_server/run_peek_server_build_only.py
peek_server/winsvc_peek_server.py
peek_server.egg-info/PKG-INFO
peek_server.egg-info/SOURCES.txt
peek_server.egg-info/dependency_links.txt
peek_server.egg-info/entry_points.txt
peek_server.egg-info/not-zip-safe
peek_server.egg-info/requires.txt
peek_server.egg-info/top_level.txt
peek_server/alembic/env.py
peek_server/alembic/script.py.mako
peek_server/alembic/versions/05cf60a0fd22_initial_setup.py
peek_server/alembic/versions/3aa82a9abe67_enabled_postgis.py
peek_server/alembic/versions/5ad8b58df646_create.py
peek_server/alembic/versions/7923ec94177a_added_peek_environent_tables.py
peek_server/alembic/versions/__init__.py
peek_server/alembic/versions/bc1622f6c16c_added_file_dir_name_to_peekappinfo.py
peek_server/alembic/versions/c2a3b93e178d_added_mssql_csvtotable.py
peek_server/alembic/versions/c5e78990adf6_added_initial_tables.py
peek_server/backend/AdminSiteResource.py
peek_server/backend/__init__.py
peek_server/backend/auth/AdminAuthChecker.py
peek_server/backend/auth/AdminAuthElement.py
peek_server/backend/auth/AdminAuthRealm.py
peek_server/backend/auth/AdminAuthResource.py
peek_server/backend/auth/AdminAuthTemplate.xml
peek_server/backend/auth/AdminUserAccess.py
peek_server/backend/auth/__init__.py
peek_server/backend/dashboard/PeekAdmDashboardListHandler.py
peek_server/backend/dashboard/__init__.py
peek_server/backend/environment/PeekAdmEnvHandler.py
peek_server/backend/environment/__init__.py
peek_server/backend/navbar/PeekAdmNavbarHandler.py
peek_server/backend/navbar/PeekAdmNavbarUserTuple.py
peek_server/backend/navbar/__init__.py
peek_server/backend/setting/PeekAdmSettingHandler.py
peek_server/backend/setting/__init__.py
peek_server/backend/update/PeekAdmCapabilitiesHandler.py
peek_server/backend/update/PeekAdmUpdatePappInfoHandler.py
peek_server/backend/update/__init__.py
peek_server/plugin/PeekServerPlatformHook.py
peek_server/plugin/ServerFrontendLoadersMixin.py
peek_server/plugin/ServerPluginLoader.py
peek_server/plugin/ServerPluginLoaderTest.py
peek_server/plugin/__init__.py
