Metadata-Version: 1.1
Name: peek-server
Version: 2.4.1
Summary: Peek Platform - Server Service
Home-page: https://github.com/Synerty/peek-server
Author: Synerty
Author-email: contact@synerty.com
License: UNKNOWN
Download-URL: https://github.com/Synerty/peek-server/tarball/2.4.1
Keywords: Peek,Python,Platform,synerty
Platform: UNKNOWN
Classifier: Programming Language :: Python :: 3.5
